<Properties>
  <MonoDevelop.Ide.Workbench ActiveDocument="func.c">
    <Files>
      <File FileName="func.c" Line="17" Column="2" />
      <File FileName="OperaterFour.c" Line="1" Column="1" />
      <File FileName="SimpleAddTwo.c" Line="1" Column="1" />
    </Files>
    <Pads>
      <Pad Id="ProjectPad">
        <State name="__root__">
          <Node name="2025.03.21" expanded="True">
            <Node name="2025.03.21" expanded="True" selected="True" />
          </Node>
        </State>
      </Pad>
    </Pads>
  </MonoDevelop.Ide.Workbench>
  <MonoDevelop.Ide.DebuggingService.PinnedWatches />
  <MonoDevelop.Ide.Workspace ActiveConfiguration="Debug|ARM64" />
  <MonoDevelop.Ide.DebuggingService.Breakpoints>
    <BreakpointStore />
  </MonoDevelop.Ide.DebuggingService.Breakpoints>
  <MultiItemStartupConfigurations />
</Properties>